cliiii/__init__.py
cliiii/main.py
cliiii/utils.py
cliiii-0.0.2.dist-info/LICENSE
cliiii-0.0.2.dist-info/METADATA
cliiii-0.0.2.dist-info/WHEEL
cliiii-0.0.2.dist-info/entry_points.txt
cliiii-0.0.2.dist-info/RECORD
